{
    "1": {
        "question": {
            "type": "text",
            "content": "How do you say “Merry Christmas” in Welsh?"
        },
        "answers": {
            "1": {
                "type": "text",
                "content": "Cer o 'ma",
                "correct": false
            },
            "2": {
                "type": "text",
                "content": "Nadolig Llawen",
                "correct": true
            },
            "3": {
                "type": "text",
                "content": "Pen dick",
                "correct": false
            },
            "4": {
                "type": "text",
                "content": "Mariah Carey",
                "correct": false
            }
        }
    },
    "2": {
        "question": {
            "type": "text",
            "content": "British nonce Cliff Richard has had how many Christmas number ones?"
        },
        "answers": {
            "1": {
                "type": "text",
                "content": "1",
                "correct": false
            },
            "2": {
                "type": "text",
                "content": "0",
                "correct": false
            },
            "3": {
                "type": "text",
                "content": "3",
                "correct": false
            },
            "4": {
                "type": "text",
                "content": "4",
                "correct": true
            }
        }
    },
    "3": {
        "question": {
            "type": "text",
            "content": "Mistletoe (Viscum album) is from the Anglo-Saxon word misteltan, which means:"
        },
        "answers": {
            "1": {
                "type": "text",
                "content": "Little dung twig",
                "correct": true
            },
            "2": {
                "type": "text",
                "content": "Windy sore bottom",
                "correct": false
            },
            "3": {
                "type": "text",
                "content": "Sharp devil tongue",
                "correct": false
            },
            "4": {
                "type": "text",
                "content": "Red berets",
                "correct": false
            }
        }
    },
    "4": {
        "question": {
            "type": "text",
            "content": "Which country were Christmas Crackers invented in?"
        },
        "answers": {
            "1": {
                "type": "text",
                "content": "Germany",
                "correct": false
            },
            "2": {
                "type": "text",
                "content": "UK",
                "correct": true
            },
            "3": {
                "type": "text",
                "content": "USA",
                "correct": false
            },
            "4": {
                "type": "text",
                "content": "Ireland",
                "correct": false
            }
        }
    },
    "5": {
        "question": {
            "type": "text",
            "content": "Which country consumes the most meat on Christmas Day?"
        },
        "answers": {
            "1": {
                "type": "text",
                "content": "USA",
                "correct": false
            },
            "2": {
                "type": "text",
                "content": "UK",
                "correct": false
            },
            "3": {
                "type": "text",
                "content": "Brazil",
                "correct": false
            },
            "4": {
                "type": "text",
                "content": "France",
                "correct": true
            }
        }
    },
    "6": {
        "question": {
            "type": "text",
            "content": "What's the biggest grossing Christmas movie of all time?"
        },
        "answers": {
            "1": {
                "type": "text",
                "content": "Elf",
                "correct": false
            },
            "2": {
                "type": "text",
                "content": "Home Alone 2",
                "correct": false
            },
            "3": {
                "type": "text",
                "content": "The Grinch",
                "correct": true
            },
            "4": {
                "type": "text",
                "content": "Home Alone",
                "correct": false
            }
        }
    },
    "7": {
        "question": {
            "type": "text",
            "content": "Which Country provides the Iconic Christmas Tree in Trafalgar Square each year?"
        },
        "answers": {
            "1": {
                "type": "text",
                "content": "Finland",
                "correct": false
            },
            "2": {
                "type": "text",
                "content": "Norway",
                "correct": true
            },
            "3": {
                "type": "text",
                "content": "Canada",
                "correct": false
            },
            "4": {
                "type": "text",
                "content": "Scotland",
                "correct": false
            }
        }
    },
    "8": {
        "question": {
            "type": "text",
            "content": "How many Reindeer does Santa have?"
        },
        "answers": {
            "1": {
                "type": "text",
                "content": "6",
                "correct": false
            },
            "2": {
                "type": "text",
                "content": "7",
                "correct": false
            },
            "3": {
                "type": "text",
                "content": "8",
                "correct": false
            },
            "4": {
                "type": "text",
                "content": "9",
                "correct": true
            }
        }
    }
}
